stxt/__init__.py
stxt/core.py
stxt-0.0.1.dist-info/METADATA
stxt-0.0.1.dist-info/WHEEL
stxt-0.0.1.dist-info/top_level.txt
stxt-0.0.1.dist-info/RECORD
