Metadata-Version: 2.4
Name: stxt
Version: 0.0.1
Summary: Official STXT library for Python (placeholder)
Author-email: Joan Costa <tu-email@ejemplo.com>
License: MIT
Project-URL: Homepage, https://stxt.dev
Project-URL: Source, https://github.com/mombiela/stxt
Requires-Python: >=3.8
